Assignment-2/codes/A2_3/A2_3.v
`timescale 1ns/1ps

// 2-input NAND gate with 1ns delay
module nand2 (
    input wire a, b,
    output wire y
);
    assign #1 y = ~(a & b);  
endmodule

// full adder
module fa (
    input wire x, y, cin,
    output wire sum, cout
);
    
    wire i1, i2, i3, i5, i6, i7; //intermediate outputs
    wire xy; // xy => x ^ y

    // first XOR => x ^ y = (x NAND (x NAND y)) NAND (y NAND (x NAND y))
    nand2 u1 (x, y, i1); // i1 = x NAND y
    nand2 u2 (x, i1, i2);
    nand2 u3 (y, i1, i3);
    nand2 u4 (i2, i3, xy);
    
    // sum = (x ^ y) ^ cin
    nand2 u5 (xy, cin, i5); // i5 = cin NAND ((x NAND (x NAND y)) NAND (y NAND (x NAND y)))
    nand2 u6 (xy, i5, i6);
    nand2 u7 (cin, i5, i7);
    nand2 u8 (i6, i7, sum);
    
    // cout = (x & y) | (cin & (x ^ y))
    nand2 u9 (i1, i5, cout); 
endmodule

// 4-bit ripple carry adder
module A2_3 #(parameter WIDTH = 4) (
    input wire [WIDTH-1:0] A, B, 
    input wire CIN,
    output wire [WIDTH-1:0] SUM,
    output wire COUT
);
    wire [WIDTH:0] carry; // intermediate cout
    assign carry[0] = CIN; // first carry is the cin

    genvar i;
    generate
        for (i = 0; i < WIDTH; i++) begin : fa
            // fa[i].fa_inst is the full adder for bit i
            fa fa_inst (
                .x(A[i]),
                .y(B[i]),
                .cin(carry[i]),
                .sum(SUM[i]),
                .cout(carry[i+1])
            );
        end
    endgenerate

    assign COUT = carry[WIDTH]; // final cout
endmodule

Assignment-2/codes/A2_3/A2_3_tb.v
`timescale 1ns/1ps;

module A2_3_tb;
    reg [3:0] A, B;
    reg CIN;
    wire [3:0] SUM;
    wire COUT;

    A2_3 dut(
        .A(A),
        .B(B),
        .CIN(CIN),
        .SUM(SUM),
        .COUT(COUT)
    );

    initial begin
        $dumpfile("A2_3/A2_3.vcd");
        $dumpvars(0, A2_3_tb);
        $monitor("Time=%0t : A = %04b B = %04b CIN = %b \t SUM = %04b COUT = %b", $time, A, B, CIN, SUM, COUT);

        // Testcase - 1
        $display("----------Testcase - 1----------");
        A = 4'b0110; // A = 6
        B = 4'b0011; // B = 3
        CIN = 0; // SUM = 6 + 3 + 0 = 9

        #100; 
        $display("\nA = %0d\tB = %0d\tCIN = %0d\tSUM = %0d\tCOUT = %0d", A, B, CIN, SUM, COUT);

        // Testcase - 2
        $display("\n----------Testcase - 2----------");
        A = 4'b0011; // A = 3
        B = 4'b1000; // B = 8
        CIN = 1; // SUM = 3 + 8 + 1 = 12

        #100;
        $display("\nA = %0d\tB = %0d\tCIN = %0d\tSUM = %0d\tCOUT = %0d", A, B, CIN, SUM, COUT);

        //Testcase - 3
        $display("\n----------Testcase - 3----------");
        A = 4'b1010; // A = 10
        B = 4'b0101; // B = 5
        CIN = 0; // SUM = 10 + 5 + 0 = 15

        #100;   
        $display("\nA = %0d\tB = %0d\tCIN = %0d\tSUM = %0d\tCOUT = %0d", A, B, CIN, SUM, COUT);

        // Testcase - 4
        $display("\n----------Testcase - 4----------");
        A = 4'b0111; // A = 7
        B = 4'b0001; // B = 1
        CIN = 0; // SUM = 7 + 1 + 0 = 8 (Worst case propagation delay because carry is propagated through all the bit positions)

        #100;
        $display("\nA = %0d\tB = %0d\tCIN = %0d\tSUM = %0d\tCOUT = %0d", A, B, CIN, SUM, COUT);
        
        // Testcase - 5
        $display("\n----------Testcase - 5----------");
        A = 4'b0010; // A = 2
        B = 4'b1101; // B = 13
        CIN = 1; // SUM = 2 + 13 + 1 = 16 (overflow)

        #100;
        $display("\nA = %0d\tB = %0d\tCIN = %0d\tSUM = %0d\tCOUT = %0d", A, B, CIN, SUM, COUT);
        $finish;
    end
endmodule

Assignment-2/codes/A2_3/A2_3.vcd
$date
	Tue Apr 22 13:33:17 2025
$end
$version
	Icarus Verilog
$end
$timescale
	1ps
$end
$scope module A2_3_tb $end
$var wire 4 ! SUM [3:0] $end
$var wire 1 " COUT $end
$var reg 4 # A [3:0] $end
$var reg 4 $ B [3:0] $end
$var reg 1 % CIN $end
$scope module dut $end
$var wire 4 & A [3:0] $end
$var wire 4 ' B [3:0] $end
$var wire 1 % CIN $end
$var wire 5 ( carry [4:0] $end
$var wire 4 ) SUM [3:0] $end
$var wire 1 " COUT $end
$var parameter 32 * WIDTH $end
$scope begin fa[0] $end
$var parameter 2 + i $end
$scope module fa_inst $end
$var wire 1 , cin $end
$var wire 1 - x $end
$var wire 1 . y $end
$var wire 1 / xy $end
$var wire 1 0 sum $end
$var wire 1 1 i7 $end
$var wire 1 2 i6 $end
$var wire 1 3 i5 $end
$var wire 1 4 i3 $end
$var wire 1 5 i2 $end
$var wire 1 6 i1 $end
$var wire 1 7 cout $end
$scope module u1 $end
$var wire 1 - a $end
$var wire 1 . b $end
$var wire 1 6 y $end
$upscope $end
$scope module u2 $end
$var wire 1 - a $end
$var wire 1 6 b $end
$var wire 1 5 y $end
$upscope $end
$scope module u3 $end
$var wire 1 . a $end
$var wire 1 6 b $end
$var wire 1 4 y $end
$upscope $end
$scope module u4 $end
$var wire 1 5 a $end
$var wire 1 4 b $end
$var wire 1 / y $end
$upscope $end
$scope module u5 $end
$var wire 1 / a $end
$var wire 1 , b $end
$var wire 1 3 y $end
$upscope $end
$scope module u6 $end
$var wire 1 / a $end
$var wire 1 3 b $end
$var wire 1 2 y $end
$upscope $end
$scope module u7 $end
$var wire 1 , a $end
$var wire 1 3 b $end
$var wire 1 1 y $end
$upscope $end
$scope module u8 $end
$var wire 1 2 a $end
$var wire 1 1 b $end
$var wire 1 0 y $end
$upscope $end
$scope module u9 $end
$var wire 1 6 a $end
$var wire 1 3 b $end
$var wire 1 7 y $end
$upscope $end
$upscope $end
$upscope $end
$scope begin fa[1] $end
$var parameter 2 8 i $end
$scope module fa_inst $end
$var wire 1 9 cin $end
$var wire 1 : x $end
$var wire 1 ; y $end
$var wire 1 < xy $end
$var wire 1 = sum $end
$var wire 1 > i7 $end
$var wire 1 ? i6 $end
$var wire 1 @ i5 $end
$var wire 1 A i3 $end
$var wire 1 B i2 $end
$var wire 1 C i1 $end
$var wire 1 D cout $end
$scope module u1 $end
$var wire 1 : a $end
$var wire 1 ; b $end
$var wire 1 C y $end
$upscope $end
$scope module u2 $end
$var wire 1 : a $end
$var wire 1 C b $end
$var wire 1 B y $end
$upscope $end
$scope module u3 $end
$var wire 1 ; a $end
$var wire 1 C b $end
$var wire 1 A y $end
$upscope $end
$scope module u4 $end
$var wire 1 B a $end
$var wire 1 A b $end
$var wire 1 < y $end
$upscope $end
$scope module u5 $end
$var wire 1 < a $end
$var wire 1 9 b $end
$var wire 1 @ y $end
$upscope $end
$scope module u6 $end
$var wire 1 < a $end
$var wire 1 @ b $end
$var wire 1 ? y $end
$upscope $end
$scope module u7 $end
$var wire 1 9 a $end
$var wire 1 @ b $end
$var wire 1 > y $end
$upscope $end
$scope module u8 $end
$var wire 1 ? a $end
$var wire 1 > b $end
$var wire 1 = y $end
$upscope $end
$scope module u9 $end
$var wire 1 C a $end
$var wire 1 @ b $end
$var wire 1 D y $end
$upscope $end
$upscope $end
$upscope $end
$scope begin fa[2] $end
$var parameter 3 E i $end
$scope module fa_inst $end
$var wire 1 F cin $end
$var wire 1 G x $end
$var wire 1 H y $end
$var wire 1 I xy $end
$var wire 1 J sum $end
$var wire 1 K i7 $end
$var wire 1 L i6 $end
$var wire 1 M i5 $end
$var wire 1 N i3 $end
$var wire 1 O i2 $end
$var wire 1 P i1 $end
$var wire 1 Q cout $end
$scope module u1 $end
$var wire 1 G a $end
$var wire 1 H b $end
$var wire 1 P y $end
$upscope $end
$scope module u2 $end
$var wire 1 G a $end
$var wire 1 P b $end
$var wire 1 O y $end
$upscope $end
$scope module u3 $end
$var wire 1 H a $end
$var wire 1 P b $end
$var wire 1 N y $end
$upscope $end
$scope module u4 $end
$var wire 1 O a $end
$var wire 1 N b $end
$var wire 1 I y $end
$upscope $end
$scope module u5 $end
$var wire 1 I a $end
$var wire 1 F b $end
$var wire 1 M y $end
$upscope $end
$scope module u6 $end
$var wire 1 I a $end
$var wire 1 M b $end
$var wire 1 L y $end
$upscope $end
$scope module u7 $end
$var wire 1 F a $end
$var wire 1 M b $end
$var wire 1 K y $end
$upscope $end
$scope module u8 $end
$var wire 1 L a $end
$var wire 1 K b $end
$var wire 1 J y $end
$upscope $end
$scope module u9 $end
$var wire 1 P a $end
$var wire 1 M b $end
$var wire 1 Q y $end
$upscope $end
$upscope $end
$upscope $end
$scope begin fa[3] $end
$var parameter 3 R i $end
$scope module fa_inst $end
$var wire 1 S cin $end
$var wire 1 T x $end
$var wire 1 U y $end
$var wire 1 V xy $end
$var wire 1 W sum $end
$var wire 1 X i7 $end
$var wire 1 Y i6 $end
$var wire 1 Z i5 $end
$var wire 1 [ i3 $end
$var wire 1 \ i2 $end
$var wire 1 ] i1 $end
$var wire 1 ^ cout $end
$scope module u1 $end
$var wire 1 T a $end
$var wire 1 U b $end
$var wire 1 ] y $end
$upscope $end
$scope module u2 $end
$var wire 1 T a $end
$var wire 1 ] b $end
$var wire 1 \ y $end
$upscope $end
$scope module u3 $end
$var wire 1 U a $end
$var wire 1 ] b $end
$var wire 1 [ y $end
$upscope $end
$scope module u4 $end
$var wire 1 \ a $end
$var wire 1 [ b $end
$var wire 1 V y $end
$upscope $end
$scope module u5 $end
$var wire 1 V a $end
$var wire 1 S b $end
$var wire 1 Z y $end
$upscope $end
$scope module u6 $end
$var wire 1 V a $end
$var wire 1 Z b $end
$var wire 1 Y y $end
$upscope $end
$scope module u7 $end
$var wire 1 S a $end
$var wire 1 Z b $end
$var wire 1 X y $end
$upscope $end
$scope module u8 $end
$var wire 1 Y a $end
$var wire 1 X b $end
$var wire 1 W y $end
$upscope $end
$scope module u9 $end
$var wire 1 ] a $end
$var wire 1 Z b $end
$var wire 1 ^ y $end
$upscope $end
$upscope $end
$upscope $end
$upscope $end
$upscope $end
$enddefinitions $end
$comment Show the parameter values. $end
$dumpall
b11 R
b10 E
b1 8
b0 +
b100 *
$end
#0
$dumpvars
x^
x]
x\
x[
xZ
xY
xX
xW
xV
0U
0T
xS
xQ
xP
xO
xN
xM
xL
xK
xJ
xI
0H
1G
xF
xD
xC
xB
xA
x@
x?
x>
x=
x<
1;
1:
x9
x7
x6
x5
x4
x3
x2
x1
x0
x/
1.
0-
0,
bx )
bx0 (
b11 '
b110 &
0%
b11 $
b110 #
x"
bx !
$end
#1000
13
11
1N
1[
16
15
0C
1P
1]
1\
#2000
09
1F
04
07
1B
1A
bx100 (
1D
0O
0V
#3000
1@
1>
1/
0<
1I
1Z
1Y
#4000
0"
02
1?
0M
b0x100 (
0^
#5000
1S
10
bx01 !
bx01 )
0=
1L
1K
b1100 (
1Q
#6000
0X
bx001 !
bx001 )
0J
#7000
b1001 !
b1001 )
1W
#100000
1,
0.
0;
1U
1-
0G
b1101 (
1%
b1000 $
b1000 '
b11 #
b11 &
#101000
03
01
14
1C
0[
05
1O
#102000
19
0F
12
11
17
0B
b1011 (
0D
1V
0I
#103000
0>
b1000 !
b1000 )
00
1<
0Z
0Y
1M
#104000
1"
0S
b1010 !
b1010 )
1=
0@
0?
1Y
1X
1^
b10011 (
0Q
#105000
1F
1Z
1?
1>
b10111 (
1D
b10 !
b10 )
0W
#106000
0"
0K
0Y
b111 (
0^
b0 !
b0 )
0=
#107000
1J
b1100 !
b1100 )
1W
#200000
0,
1.
1H
0U
0-
1T
b110 (
0%
b101 $
b101 '
b1010 #
b1010 &
#201000
13
04
0N
1[
15
0\
#202000
09
02
b100 (
07
1I
#203000
1@
b1101 !
b1101 )
10
0M
0L
#204000
0F
1S
0?
0D
1L
1K
b1000 (
1Q
#205000
1M
0Z
0X
1=
b1011 !
b1011 )
0J
#206000
0S
1"
0L
0Q
1Y
1X
b10000 (
1^
#207000
1Z
1J
b111 !
b111 )
0W
#208000
0"
0Y
b0 (
0^
#209000
b1111 !
b1111 )
1W
#300000
0H
1-
1G
0T
b1 $
b1 '
b111 #
b111 &
#301000
1N
06
05
0O
1\
#302000
19
15
14
b10 (
17
0V
#303000
0@
0>
0/
1Y
#304000
1F
1?
1>
b110 (
1D
12
b111 !
b111 )
0W
#305000
0M
0K
0=
b100 !
b100 )
00
#306000
1S
1L
1K
b1110 (
1Q
#307000
0X
b0 !
b0 )
0J
#308000
b1000 !
b1000 )
1W
#400000
1,
1H
1U
0-
0G
b1111 (
1%
b1101 $
b1101 '
b10 #
b10 &
#401000
01
0N
0[
16
1O
#402000
09
b1001 !
b1001 )
10
1V
04
b1101 (
07
#403000
1@
0Z
0Y
1/
#404000
0F
1"
0?
0D
1Y
1X
b11001 (
1^
03
02
#405000
19
1M
1=
b11 !
b11 )
0W
12
11
b11011 (
17
#406000
0S
0@
0>
0L
b10011 (
0Q
b10 !
b10 )
00
#407000
1F
1Z
1?
1>
b10111 (
1D
b110 !
b110 )
1J
#408000
0"
0M
0K
0Y
b111 (
0^
b100 !
b100 )
0=
#409000
1S
1L
1K
b1111 (
1Q
b1100 !
b1100 )
1W
#410000
0Z
0X
b1000 !
b1000 )
0J
#411000
1"
1Y
1X
b11111 (
1^
#412000
b0 !
b0 )
0W
