Assignment-1/codes/A1_2/A1_2.v
module A1_2 (
    input clk, // Clock signal
    input reset, // Asynchronous reset signal (active high {1 is high})
    input enable, // Control signal to enable counting
    output reg [3:0] count);

    always@(posedge clk or posedge reset) begin
        if (reset)              // Counter is cleared when reset is high
            count <= 4'b0000;   // We use '<=' in place of '=' for "non-blocking assignments" i.e., when we  use "always@(posedge clk)" block.
        else if (enable)        // Counting takes place only when enable is high
            count <= count + 1;
    end
endmodule

Assignment-1/codes/A1_2/A1_2_tb.v
module A1_2_tb;

    reg clk;
    reg reset;
    reg enable;
    wire [3:0] count;

    A1_2 uut (
        .clk(clk),
        .reset(reset),
        .enable(enable),
        .count(count)
    );

    // Clock generation: toggles every 5 time units (10 time unit period)
    always #5 clk = ~clk;

    initial begin
        $dumpfile("A1_2/A1_2.vcd");
        $dumpvars(0, A1_2_tb);
        $dumpvars(0, uut);

        // Initialize signals
        clk = 0;
        reset = 1;  // Start with reset asserted
        enable = 0;

        #7 reset = 0;      // Deassert reset at time 7 (not on clock edge)
        #3 enable = 1;     // Start counting at time 10

        #100 enable = 0;    // Stop counting
        
        // Test asynchronous reset - assert reset between clock edges
        #12 reset = 1;      // Assert reset at time 122 (between clock edges)
        #3 reset = 0;       // Deassert reset at time 125
        
        #7 enable = 1;     // Start counting again
        #60;

        $finish;
    end

endmodule

Assignment-1/codes/A1_2/A1_2.vcd
$date
	Fri Apr 11 22:26:42 2025
$end
$version
	Icarus Verilog
$end
$timescale
	1s
$end
$scope module A1_2_tb $end
$var wire 4 ! count [3:0] $end
$var reg 1 " clk $end
$var reg 1 # enable $end
$var reg 1 $ reset $end
$scope module uut $end
$var wire 1 " clk $end
$var wire 1 # enable $end
$var wire 1 $ reset $end
$var reg 4 % count [3:0] $end
$upscope $end
$upscope $end
$scope module A1_2_tb $end
$scope module uut $end
$upscope $end
$upscope $end
$enddefinitions $end
$comment Show the parameter values. $end
$dumpall
$end
#0
$dumpvars
b0 %
1$
0#
0"
b0 !
$end
#5
1"
#7
0$
#10
1#
0"
#15
b1 !
b1 %
1"
#20
0"
#25
b10 !
b10 %
1"
#30
0"
#35
b11 !
b11 %
1"
#40
0"
#45
b100 !
b100 %
1"
#50
0"
#55
b101 !
b101 %
1"
#60
0"
#65
b110 !
b110 %
1"
#70
0"
#75
b111 !
b111 %
1"
#80
0"
#85
b1000 !
b1000 %
1"
#90
0"
#95
b1001 !
b1001 %
1"
#100
0"
#105
b1010 !
b1010 %
1"
#110
0"
0#
#115
1"
#120
0"
#122
b0 !
b0 %
1$
#125
0$
1"
#130
0"
#132
1#
#135
b1 !
b1 %
1"
#140
0"
#145
b10 !
b10 %
1"
#150
0"
#155
b11 !
b11 %
1"
#160
0"
#165
b100 !
b100 %
1"
#170
0"
#175
b101 !
b101 %
1"
#180
0"
#185
b110 !
b110 %
1"
