Assignment-1/codes/A1_1/A1_1.v
module A1_1 (
    input [3:0] in,
    output reg [1:0] out, 
    output reg valid);

    // We are using 'reg' for both "out" and "valid" because we are doing Procedural Assignment (always block)

    always@(*) begin
        valid = 1'b1;
        casez(in)
            4'b1zzz: out = 2'b11; 
            4'b01zz: out = 2'b10;
            4'b001z: out = 2'b01;
            4'b0001: out = 2'b00;
            default: begin
                out = 2'b00;
                valid = 1'b0;
            end
        endcase
    end

endmodule

Assignment-1/codes/A1_1/A1_1_tb.v
module A1_1_tb;
    reg [3:0] in;
    wire [1:0] out;
    wire valid;

    // DUT instantiation
    A1_1 uut (
        .in(in),
        .out(out),
        .valid(valid)
    );

    initial begin
        $dumpfile("A1_1/A1_1.vcd");
        $dumpvars(0, A1_1_tb);
        $dumpvars(0, uut);

        $display("Time\tin\tout\tvalid");
        $monitor("%0t\t%b\t%b\t%b", $time, in, out, valid);

        // Apply test inputs (16 total)
        in = 4'b0000; #10;
        in = 4'b0001; #10;
        in = 4'b0010; #10;
        in = 4'b0011; #10;
        in = 4'b0100; #10;
        in = 4'b0101; #10;
        in = 4'b0110; #10;
        in = 4'b0111; #10;
        in = 4'b1000; #10;
        in = 4'b1001; #10;
        in = 4'b1010; #10;
        in = 4'b1011; #10;
        in = 4'b1100; #10;
        in = 4'b1101; #10;
        in = 4'b1110; #10;
        in = 4'b1111; #10;

        $finish;
    end
endmodule

Assignment-1/codes/A1_1/A1_1.vcd
$date
	Thu Apr 17 12:47:56 2025
$end
$version
	Icarus Verilog
$end
$timescale
	1s
$end
$scope module A1_1_tb $end
$var wire 1 ! valid $end
$var wire 2 " out [1:0] $end
$var reg 4 # in [3:0] $end
$scope module uut $end
$var wire 4 $ in [3:0] $end
$var reg 2 % out [1:0] $end
$var reg 1 ! valid $end
$upscope $end
$upscope $end
$scope module A1_1_tb $end
$scope module uut $end
$upscope $end
$upscope $end
$enddefinitions $end
$comment Show the parameter values. $end
$dumpall
$end
#0
$dumpvars
b0 %
b0 $
b0 #
b0 "
0!
$end
#10
1!
b1 #
b1 $
#20
b1 "
b1 %
b10 #
b10 $
#30
b11 #
b11 $
#40
b10 "
b10 %
b100 #
b100 $
#50
b101 #
b101 $
#60
b110 #
b110 $
#70
b111 #
b111 $
#80
b11 "
b11 %
b1000 #
b1000 $
#90
b1001 #
b1001 $
#100
b1010 #
b1010 $
#110
b1011 #
b1011 $
#120
b1100 #
b1100 $
#130
b1101 #
b1101 $
#140
b1110 #
b1110 $
#150
b1111 #
b1111 $
